django_payments_chile/FlowProvider.py
django_payments_chile/KhipuProvider.py
django_payments_chile/WebpayProvider.py
django_payments_chile/__init__.py
django_payments_chile/clientes.py
django_payments_chile/providers.py
django_payments_chile/version.py
django_payments_chile-2024.12.5.dist-info/LICENSE
django_payments_chile-2024.12.5.dist-info/METADATA
django_payments_chile-2024.12.5.dist-info/WHEEL
django_payments_chile-2024.12.5.dist-info/RECORD
