Metadata-Version: 2.3
Name: django-payments-chile
Version: 2024.12.5
Summary: Pasarelas de pago chilenas para django-payments
Home-page: https://mariofix.github.io/django-payments-chile/
License: MIT
Keywords: flow,khipu,kushki,transbank,payku,pagofacil,webpay,onepay,pagos,django,payment,django-payments
Author: Mario Hernandez
Author-email: mariofix@proton.me
Requires-Python: >=3.9,<4.0
Classifier: Development Status :: 4 - Beta
Classifier: License :: OSI Approved :: MIT License
Classifier: Programming Language :: Python :: 3.9
Classifier: Programming Language :: Python :: 3.10
Classifier: Programming Language :: Python :: 3.11
Classifier: Programming Language :: Python :: 3.12
Classifier: Intended Audience :: Developers
Classifier: Intended Audience :: Information Technology
Classifier: Topic :: Software Development :: Libraries :: Python Modules
Classifier: Framework :: Django
Classifier: Operating System :: OS Independent
Provides-Extra: dev
Requires-Dist: black ; extra == "dev"
Requires-Dist: cairosvg ; extra == "dev"
Requires-Dist: coverage ; extra == "dev"
Requires-Dist: dj-database-url ; extra == "dev"
Requires-Dist: django-payments (>=2.0,<4.0)
Requires-Dist: factory-boy ; extra == "dev"
Requires-Dist: faker ; extra == "dev"
Requires-Dist: isort ; extra == "dev"
Requires-Dist: lxml ; extra == "dev"
Requires-Dist: mkdocs ; extra == "dev"
Requires-Dist: mkdocs-git-revision-date-localized-plugin ; extra == "dev"
Requires-Dist: mkdocs-material ; extra == "dev"
Requires-Dist: mkdocstrings[python] ; extra == "dev"
Requires-Dist: pillow ; extra == "dev"
Requires-Dist: pre-commit ; extra == "dev"
Requires-Dist: pytest ; extra == "dev"
Requires-Dist: pytest-cov ; extra == "dev"
Requires-Dist: pytest-django ; extra == "dev"
Requires-Dist: pytest-mock ; extra == "dev"
Requires-Dist: requests
Requires-Dist: tox ; extra == "dev"
Requires-Dist: tox-gh-actions ; extra == "dev"
Project-URL: Documentation, https://mariofix.github.io/django-payments-chile/
Project-URL: Repository, https://github.com/mariofix/django-payments-chile
